dvg_ringbuffer.py
dvg_ringbuffer-1.1.0.dist-info/AUTHORS.rst
dvg_ringbuffer-1.1.0.dist-info/LICENSE.txt
dvg_ringbuffer-1.1.0.dist-info/METADATA
dvg_ringbuffer-1.1.0.dist-info/WHEEL
dvg_ringbuffer-1.1.0.dist-info/top_level.txt
dvg_ringbuffer-1.1.0.dist-info/RECORD
