Metadata-Version: 2.1
Name: dvg-ringbuffer
Version: 1.1.0
Summary: Numpy ring buffer at a fixed memory address to allow for significantly sped up numpy, sigpy, numba & pyFFTW calculations.
Home-page: https://github.com/Dennis-van-Gils/python-dvg-ringbuffer
Author: Dennis van Gils
Author-email: vangils.dennis@gmail.com
License: MIT
Project-URL: Issue Tracker, https://github.com/Dennis-van-Gils/python-dvg-ringbuffer/issues
Keywords: ring buffer,circular buffer,numpy-ringbuffer,numpy,scipy,numba,pyFFTW,deque,speed,fast
Classifier: Development Status :: 5 - Production/Stable
Classifier: License :: OSI Approved :: MIT License
Classifier: Intended Audience :: Developers
Classifier: Intended Audience :: Science/Research
Classifier: Operating System :: OS Independent
Classifier: Programming Language :: Python
Classifier: Programming Language :: Python :: 3
Classifier: Topic :: Scientific/Engineering 
Classifier: Topic :: Scientific/Engineering :: Information Analysis
Classifier: Topic :: Scientific/Engineering :: Electronic Design Automation (EDA)
Classifier: Topic :: Scientific/Engineering :: Physics
Requires-Python: ~=3.0
License-File: LICENSE.txt
License-File: AUTHORS.rst
Requires-Dist: numpy <3.0,>=1.15
